pixeldrainuploader/__init__.py
pixeldrainuploader/core.py
pixeldrainuploader/utils.py
pixeldrainuploader/__metadata__/DISCLIAIMER.md
pixeldrainuploader/__metadata__/LICENSE
pixeldrainuploader/__metadata__/README.md
pixeldrainuploader/__metadata__/__init__.py
pixeldrainuploader/__metadata__/requirements.txt
pixeldrainuploader-0.4.0.dist-info/METADATA
pixeldrainuploader-0.4.0.dist-info/WHEEL
pixeldrainuploader-0.4.0.dist-info/top_level.txt
pixeldrainuploader-0.4.0.dist-info/RECORD
