Metadata-Version: 2.1
Name: pixeldrainuploader
Version: 0.4.0
Summary: Simple uploader for pixeldrain. This library uses third-party web services by default (see `test_opt_out.py`).
Home-page: http://code.foxe6.kozow.com/pixeldrainuploader/
Author: f̣ộx̣ệ6
Author-email: foxe6@pm.me
License: AGPL-3.0
Project-URL: Sourcecode, http://code.foxe6.kozow.com/pixeldrainuploader.zip
Project-URL: Documentation, http://code.foxe6.kozow.com/pixeldrainuploader/docs/
Project-URL: Example, http://code.foxe6.kozow.com/pixeldrainuploader/test/
Project-URL: Funding, https://paypal.me/foxe6
Project-URL: Say Thanks!, https://saythanks.io/to/foxe6
Keywords: pixeldrain upload uploader manager batch
Platform: UNKNOWN
Classifier: Programming Language :: Python :: 3.9
Classifier: Topic :: Utilities
Classifier: Natural Language :: English
Classifier: Intended Audience :: Developers
Classifier: License :: OSI Approved :: GNU Affero General Public License v3
Classifier: Operating System :: MacOS
Classifier: Operating System :: POSIX
Classifier: Operating System :: Microsoft :: Windows :: Windows 10
Classifier: Development Status :: 5 - Production/Stable
Requires-Python: >=3.5
Requires-Dist: requests (>=0.0.1)
Requires-Dist: omnitools (>=0.0.1)
Requires-Dist: cloudscraper (>=0.0.1)
Requires-Dist: threadwrapper (>=0.0.1)
